vnoise/__init__.py
vnoise/_tables.py
vnoise/vnoise.py
vnoise-0.1.0.dist-info/LICENSE
vnoise-0.1.0.dist-info/METADATA
vnoise-0.1.0.dist-info/WHEEL
vnoise-0.1.0.dist-info/top_level.txt
vnoise-0.1.0.dist-info/RECORD
