Metadata-Version: 2.1
Name: vnoise
Version: 0.1.0
Summary: Vectorized, pure-Python Perlin noise library
Home-page: https://github.com/plottertools/vnoise
Author: Antoine Beyeler
Author-email: abeyeler@ab-ware.com
License: MIT
Platform: UNKNOWN
Classifier: License :: OSI Approved :: MIT License
Classifier: Operating System :: OS Independent
Classifier: Programming Language :: Python :: 3
Classifier: Topic :: Multimedia :: Graphics
Classifier: Typing :: Typed
Requires-Python: >=3.6
